isopsephism/isopsephism.py
isopsephism-0.1.dist-info/LICENSE
isopsephism-0.1.dist-info/METADATA
isopsephism-0.1.dist-info/WHEEL
isopsephism-0.1.dist-info/top_level.txt
isopsephism-0.1.dist-info/RECORD
