Metadata-Version: 2.1
Name: isopsephism
Version: 0.1
Summary: Find the numerical value of words.
Author: Uggerus
License: Apache-2.0
Project-URL: Homepage, https://github.com/uggerus/isopsephism
Project-URL: Changelog, https://github.com/uggerus/isopsephism/releases
Project-URL: Issues, https://github.com/uggerus/isopsephism/issues
Project-URL: CI, https://github.com/uggerus/isopsephism/actions
Classifier: License :: OSI Approved :: Apache Software License
Requires-Python: >=3.8
License-File: LICENSE
Provides-Extra: test
Requires-Dist: pytest ; extra == 'test'
